{"problemID": 336, "optimal_cost": 16, "pacman": {"x": 7, "y": 2}, "map": [[1, 1, 1, 1, 1, 1, 1, 1, 1, 1, 1, 1], [1, 3, 2, 2, 3, 3, 3, 3, 3, 3, 3, 1], [1, 3, 3, 3, 3, 3, 3, 5, 3, 3, 3, 1], [1, 3, 3, 3, 3, 3, 3, 3, 3, 3, 3, 1], [1, 3, 3, 2, 3, 3, 3, 3, 3, 3, 3, 1], [1, 3, 3, 3, 3, 3, 3, 2, 3, 3, 3, 1], [1, 3, 3, 3, 3, 3, 3, 3, 2, 3, 3, 1], [1, 3, 3, 3, 3, 3, 3, 3, 3, 3, 3, 1], [1, 3, 3, 3, 3, 3, 3, 3, 3, 3, 3, 1], [1, 3, 3, 3, 3, 3, 3, 3, 3, 3, 3, 1], [1, 3, 3, 3, 3, 3, 3, 3, 3, 3, 3, 1], [1, 1, 1, 1, 1, 1, 1, 1, 1, 1, 1, 1]], "num_goals": 5, "optimal_map": [[1, 1, 1, 1, 1, 1, 1, 1, 1, 1, 1, 1], [1, 3, 15, 14, 3, 3, 3, 3, 3, 3, 3, 1], [1, 3, 3, 3, 3, 3, 3, 5, 3, 3, 3, 1], [1, 3, 3, 3, 3, 3, 3, 3, 3, 3, 3, 1], [1, 3, 3, 13, 3, 3, 3, 3, 3, 3, 3, 1], [1, 3, 3, 3, 3, 3, 3, 11, 3, 3, 3, 1], [1, 3, 3, 3, 3, 3, 3, 3, 12, 3, 3, 1], [1, 3, 3, 3, 3, 3, 3, 3, 3, 3, 3, 1], [1, 3, 3, 3, 3, 3, 3, 3, 3, 3, 3, 1], [1, 3, 3, 3, 3, 3, 3, 3, 3, 3, 3, 1], [1, 3, 3, 3, 3, 3, 3, 3, 3, 3, 3, 1], [1, 1, 1, 1, 1, 1, 1, 1, 1, 1, 1, 1]]}